kpu/__init__.py
kpu/client/__init__.py
kpu/client/cluster.py
kpu/client/compute.py
kpu/client/context.py
kpu/client/decorator.py
kpu/client/event.py
kpu/client/grpc.py
kpu/client/init.py
kpu/client/metrics.py
kpu/client/aio/__init__.py
kpu/client/aio/api_client.py
kpu/client/aio/discovery.py
kpu/client/aio/dynamic.py
kpu/client/aio/resource.py
kpu/client/aio/rest.py
kpu/client/aio/stream.py
kpu/client/aio/watch.py
kpu/server/__init__.py
kpu/server/health/__init__.py
kpu/server/health/health.proto
kpu/server/health/health.py
kpu/server/health/health_pb2.py
kpu/server/health/health_pb2.pyi
kpu/server/health/health_pb2_grpc.py
kpu/server/metrics/__init__.py
kpu/server/metrics/metrics.proto
kpu/server/metrics/metrics_pb2.py
kpu/server/metrics/metrics_pb2.pyi
kpu/server/metrics/metrics_pb2_grpc.py
kpu/server/metrics/service.py
kpu/server/metrics/source.py
kpu/server/nvidia/__init__.py
kpu/server/nvidia/metrics.py
kpu/torch/__init__.py
kpu/torch/backend/__init__.py
kpu/torch/backend/_async.py
kpu/torch/backend/_client.py
kpu/torch/backend/_device.py
kpu/torch/backend/_driver.py
kpu/torch/backend/_runtime.py
kpu/torch/backend/_storage.py
kpu/torch/backend/setup.py
kpu/torch/backend/aten/__init__.py
kpu/torch/backend/aten/copy.py
kpu/torch/backend/aten/dispatch.py
kpu/torch/backend/aten/scalar.py
kpu/torch/client/__init__.py
kpu/torch/client/metadata.py
kpu/torch/client/service.py
kpu/torch/client/tensor.py
kpu/torch/client/utils.py
kpu/torch/server/__init__.py
kpu/torch/server/__main__.py
kpu/torch/server/compute.py
kpu/torch/server/serialization.py
kpu/torch/server/server.py
kpu/torch/server/service.proto
kpu/torch/server/service.py
kpu/torch/server/service_pb2.py
kpu/torch/server/service_pb2.pyi
kpu/torch/server/service_pb2_grpc.py
kpu/torch/server/storage.py
vpu-0.1.0.dev1.dist-info/licenses/LICENSE
vpu-0.1.0.dev1.dist-info/METADATA
vpu-0.1.0.dev1.dist-info/WHEEL
vpu-0.1.0.dev1.dist-info/top_level.txt
vpu-0.1.0.dev1.dist-info/RECORD
