Metadata-Version: 2.4
Name: vpu
Version: 0.1.0.dev1
Summary: Virtual Processing Unit
Author-email: Antonin Stefanutti <antonin.stefanutti@gmail.com>
License: Apache-2.0
Project-URL: Homepage, https://github.com/astefanutti/kpu
Project-URL: Repository, https://github.com/astefanutti/kpu
Project-URL: Issues, https://github.com/astefanutti/kpu/issues
Keywords: pytorch,kubernetes
Classifier: Development Status :: 3 - Alpha
Classifier: Intended Audience :: Developers
Classifier: Intended Audience :: Science/Research
Classifier: Programming Language :: Python :: 3
Classifier: Programming Language :: Python :: 3.10
Classifier: Programming Language :: Python :: 3.11
Classifier: Programming Language :: Python :: 3.12
Classifier: Programming Language :: Python :: 3.13
Classifier: Programming Language :: Python :: 3.14
Requires-Python: >=3.10
License-File: LICENSE
Requires-Dist: grpcio>=1.60.0
Requires-Dist: kubernetes>=33.0.0
Requires-Dist: protobuf>=6.31.0
Requires-Dist: aiohttp<4.0.0,>=3.9.0
Requires-Dist: pydantic>=2.10.0
Provides-Extra: dev
Requires-Dist: grpcio-tools>=1.60.0; extra == "dev"
Requires-Dist: pytest>=7.0.0; extra == "dev"
Requires-Dist: pytest-asyncio>=0.21.0; extra == "dev"
Requires-Dist: black>=23.0.0; extra == "dev"
Requires-Dist: ruff>=0.1.0; extra == "dev"
Requires-Dist: mypy>=1.0.0; extra == "dev"
Provides-Extra: test
Requires-Dist: pytest>=7.0.0; extra == "test"
Requires-Dist: pytest-asyncio>=0.21.0; extra == "test"
Provides-Extra: torch
Requires-Dist: torch>=2.1.0; extra == "torch"
Provides-Extra: examples
Requires-Dist: torchvision>=0.24.0; extra == "examples"
Dynamic: license-file
